CHANGES.txt
README.txt
setup.py
src/hexagonit/__init__.py
src/hexagonit.decorators.egg-info/PKG-INFO
src/hexagonit.decorators.egg-info/SOURCES.txt
src/hexagonit.decorators.egg-info/dependency_links.txt
src/hexagonit.decorators.egg-info/namespace_packages.txt
src/hexagonit.decorators.egg-info/requires.txt
src/hexagonit.decorators.egg-info/top_level.txt
src/hexagonit.decorators.egg-info/zip-safe
src/hexagonit/decorators/README.txt
src/hexagonit/decorators/__init__.py
src/hexagonit/decorators/browser.py
src/hexagonit/decorators/edgecases.txt
src/hexagonit/decorators/tests.py
