Metadata-Version: 1.0
Name: hexagonit.decorators
Version: 0.2
Summary: Collection of useful decorators for Zope development
Home-page: http://pypi.python.org/pypi/hexagonit.decorators
Author: Kai Lautaportti
Author-email: kai.lautaportti@hexagonit.fi
License: GPL
Platform: UNKNOWN
Classifier: Framework :: Plone
Classifier: Framework :: Zope2
Classifier: Framework :: Zope3
Classifier: Intended Audience :: Developers
Classifier: License :: OSI Approved :: GNU General Public License (GPL)
Classifier: Programming Language :: Python
Classifier: Topic :: Software Development :: Libraries :: Python Modules
